ai_network_envoy_sdk/__init__.py
ai_network_envoy_sdk/ai_network_envoy_pb2.py
ai_network_envoy_sdk/ai_network_envoy_pb2_grpc.py
ai_network_envoy_sdk/instruction_parser.py
ai_network_envoy_sdk/internal.py
ai_network_envoy_sdk-0.2.0.dist-info/METADATA
ai_network_envoy_sdk-0.2.0.dist-info/WHEEL
ai_network_envoy_sdk-0.2.0.dist-info/top_level.txt
ai_network_envoy_sdk-0.2.0.dist-info/RECORD
