Metadata-Version: 2.1
Name: ai-network-envoy-sdk
Version: 0.2.0
Summary: SDK for AI Network P2P message, dataset, mdoel, file sharing system
Home-page: UNKNOWN
Author: kmh4500
Author-email: kimminhyun@comcom.ai
License: UNKNOWN
Platform: UNKNOWN
Requires-Dist: grpcio
Requires-Dist: grpcio-tools
